edf_plasma_core/__init__.py
edf_plasma_core/__version__.py
edf_plasma_core/dissector.py
edf_plasma_core/concept/__init__.py
edf_plasma_core/concept/tag.py
edf_plasma_core/helper/__init__.py
edf_plasma_core/helper/cryptography.py
edf_plasma_core/helper/csv.py
edf_plasma_core/helper/datetime.py
edf_plasma_core/helper/filtering.py
edf_plasma_core/helper/glob.py
edf_plasma_core/helper/hashing.py
edf_plasma_core/helper/identifying.py
edf_plasma_core/helper/json.py
edf_plasma_core/helper/logging.py
edf_plasma_core/helper/matching.py
edf_plasma_core/helper/perfmeter.py
edf_plasma_core/helper/streaming.py
edf_plasma_core/helper/table.py
edf_plasma_core/helper/typing.py
edf_plasma_core/helper/xml.py
edf_plasma_core-1.0.0.dist-info/licenses/LICENSE
edf_plasma_core-1.0.0.dist-info/METADATA
edf_plasma_core-1.0.0.dist-info/WHEEL
edf_plasma_core-1.0.0.dist-info/top_level.txt
edf_plasma_core-1.0.0.dist-info/RECORD
