Metadata-Version: 2.4
Name: edf-plasma-core
Version: 1.0.0
Summary: EDF Plasma Core
Author-email: CERT-EDF <cert@edf.fr>
License-Expression: MIT
Project-URL: Homepage, https://github.com/cert-edf/plasma
Project-URL: Repository, https://github.com/cert-edf/plasma
Project-URL: Bug Tracker, https://github.com/cert-edf/plasma/issues
Keywords: edf,plasma,forensic,artifact,dissector,normalizer,core
Classifier: Development Status :: 5 - Production/Stable
Classifier: Intended Audience :: End Users/Desktop
Classifier: Operating System :: POSIX :: Linux
Classifier: Programming Language :: Python :: 3
Classifier: Programming Language :: Python :: 3 :: Only
Classifier: Topic :: Utilities
Classifier: Topic :: Security
Requires-Python: >=3.12
License-File: LICENSE
Requires-Dist: yarl~=1.9
Requires-Dist: rich~=14.1
Requires-Dist: magika~=0.5
Requires-Dist: python-magic~=0.4
Dynamic: license-file
